[
  {
    "id": 1,
    "name": "BOT",
    "total_space": null,
    "remaining_space": 281,
    "updateTime": "2026-07-23 23:20:15"
  },
  {
    "id": 5,
    "name": "TSA",
    "total_space": null,
    "remaining_space": 220,
    "updateTime": "2026-07-23 23:20:14"
  },
  {
    "id": 6,
    "name": "RD1 A",
    "total_space": null,
    "remaining_space": 24,
    "updateTime": "2026-07-23 23:20:16"
  },
  {
    "id": 7,
    "name": "RD1 B",
    "total_space": null,
    "remaining_space": 13,
    "updateTime": "2026-07-23 23:20:17"
  }
]
