[
  {
    "id": 1,
    "name": "BOT",
    "total_space": null,
    "remaining_space": 291,
    "updateTime": "2026-07-20 01:20:15"
  },
  {
    "id": 5,
    "name": "TSA",
    "total_space": null,
    "remaining_space": 218,
    "updateTime": "2026-07-20 01:20:15"
  },
  {
    "id": 6,
    "name": "RD1 A",
    "total_space": null,
    "remaining_space": 38,
    "updateTime": "2026-07-20 01:20:12"
  },
  {
    "id": 7,
    "name": "RD1 B",
    "total_space": null,
    "remaining_space": 19,
    "updateTime": "2026-07-20 01:20:14"
  }
]
