[
  {
    "id": 1,
    "name": "BOT",
    "total_space": null,
    "remaining_space": 303,
    "updateTime": "2026-07-22 04:10:16"
  },
  {
    "id": 5,
    "name": "TSA",
    "total_space": null,
    "remaining_space": 218,
    "updateTime": "2026-07-22 04:10:14"
  },
  {
    "id": 6,
    "name": "RD1 A",
    "total_space": null,
    "remaining_space": 36,
    "updateTime": "2026-07-22 04:10:15"
  },
  {
    "id": 7,
    "name": "RD1 B",
    "total_space": null,
    "remaining_space": 18,
    "updateTime": "2026-07-22 04:10:17"
  }
]
